meteoserver/__init__.py
meteoserver/help.py
meteoserver/sundata.py
meteoserver/weatherforecast.py
meteoserver-0.0.19.dist-info/licenses/LICENCE
meteoserver-0.0.19.dist-info/METADATA
meteoserver-0.0.19.dist-info/WHEEL
meteoserver-0.0.19.dist-info/top_level.txt
meteoserver-0.0.19.dist-info/RECORD
