Metadata-Version: 2.4
Name: meteoserver
Version: 0.0.19
Summary: A Python module to obtain and read Dutch weather data from Meteoserver.nl
Author-email: Marc van der Sluys <git@vandersluys.nl>
License-Expression: GPL-3.0-or-later
Project-URL: GitHub, https://github.com/MarcvdSluys/Meteoserver
Project-URL: ReadTheDocs, https://meteoserver.readthedocs.io
Keywords: weather,sun,data,forecast,api
Classifier: Development Status :: 4 - Beta
Classifier: Intended Audience :: Developers
Classifier: Intended Audience :: Education
Classifier: Intended Audience :: Science/Research
Classifier: Natural Language :: English
Classifier: Operating System :: OS Independent
Classifier: Programming Language :: Python :: 3
Classifier: Topic :: Scientific/Engineering
Classifier: Topic :: Scientific/Engineering :: Physics
License-File: LICENCE
Requires-Dist: pandas
Requires-Dist: requests
Dynamic: license-file
